Metadata-Version: 1.2
Name: attendanceMarker
Version: 0.0.1
Summary: Compares excel files from webex and compares with roll call to mark attendance
Home-page: https://github.com/dipayan90/attendancemarker
Author: Dipayan Chattopadhyay
Author-email: dipayan90@gmail.com
License: MIT
Download-URL: https://github.com/dipayan90/attendancemarker/archive/0.0.1.tar.gz
Platform: UNKNOWN
Classifier: Development Status :: 3 - Alpha
Classifier: Intended Audience :: Developers
Classifier: Topic :: Software Development :: Libraries
Classifier: License :: OSI Approved :: MIT License
Classifier: Programming Language :: Python :: 3.8
Requires-Python: >=0.0.1
